[
    {
      "id": 1,
      "image": "got-1.jpg"
    },
    {
      "id": 2,
      "image": "got-2.jpg"    
    },
    {
      "id": 3,
      "image": "got-3.jpg"
    },
    {
      "id": 4,
      "image": "got-4.jpg" 
    },
    {
      "id": 5,
      "image": "got-5.jpg"
    },
    {
      "id": 6,
      "image": "got-6.jpg"
    },
    {
      "id": 7,
      "image": "got-7.jpg"
    },
    {
      "id": 8,
      "image": "got-8.jpg"
    },
    {
      "id": 9,
      "image": "got-9.jpg"
    },
    {
      "id": 10,
      "image": "got-10.jpg"
    },
    {
      "id": 11,
      "image": "got-11.jpg"
    },
    {
      "id": 12,
      "image": "got-12.jpg"
    }
  ]
  